LRC/__init__.py
LRC/client_main.py
LRC/server_main.py
LRC/Client/ButtonContainer.py
LRC/Client/ClientUI.py
LRC/Client/ControllerCollectionBuildScreen.py
LRC/Client/ControllerCollectionScreen.py
LRC/Client/ControllerEditor.py
LRC/Client/ControllerScreen.py
LRC/Client/LRCClient.py
LRC/Client/LRCClientConnector.py
LRC/Client/__init__.py
LRC/Common/Exceptions.py
LRC/Common/__init__.py
LRC/Common/empty.py
LRC/Common/info.py
LRC/Common/logger.py
LRC/Common/utilities.py
LRC/Controller/LRCController.py
LRC/Controller/LRCKeySettings.py
LRC/Controller/__init__.py
LRC/Controller/win32keydefines.py
LRC/Examples/__init__.py
LRC/Protocol/BaseCommunicationProtocol.py
LRC/Protocol/BaseProtocol.py
LRC/Protocol/__init__.py
LRC/Protocol/v1/BaseProtocol.py
LRC/Protocol/v1/ClientProtocol.py
LRC/Protocol/v1/CommandServerProtocol.py
LRC/Protocol/v1/ServerProtocol.py
LRC/Protocol/v1/WaiterProtocol.py
LRC/Protocol/v1/__init__.py
LRC/Server/Command.py
LRC/Server/CommandServer.py
LRC/Server/Config.py
LRC/Server/LRCServer.py
LRC/Server/ServerUI.py
LRC/Server/__init__.py
LRC/Server/Commands/CommandTest.py
LRC/Server/Commands/LRCServer.py
LRC/Server/Commands/__init__.py
LRC/Utilities/__init__.py
LRC/Utilities/distribution.py
LRC/lrccollections/Kugou.json
LRC/lrccollections/PotPlayer.json
LRC/lrccollections/__init__.py
LRC-0.1.5.dist-info/METADATA
LRC-0.1.5.dist-info/RECORD
LRC-0.1.5.dist-info/WHEEL
LRC-0.1.5.dist-info/entry_points.txt
LRC-0.1.5.dist-info/top_level.txt
