Metadata-Version: 2.1
Name: LRC
Version: 0.1.5
Summary: A lan remote controller to keyboard associated devices.
Home-page: https://github.com/davied9/LANRemoteController
Author: Davied Paul
Author-email: wuwei_543333827@126.com
License: UNKNOWN
Platform: UNKNOWN
Classifier: Programming Language :: Python
Requires-Dist: PyUserInput (>=0.1.9)
Requires-Dist: pypiwin32 (>=223); platform_system == "Windows"
